trajdata/__init__.py
trajdata/dataset.py
trajdata/omega_prime_trajdata.py
trajdata/augmentation/__init__.py
trajdata/augmentation/augmentation.py
trajdata/augmentation/low_vel_yaw_correction.py
trajdata/augmentation/noise_histories.py
trajdata/caching/__init__.py
trajdata/caching/df_cache.py
trajdata/caching/env_cache.py
trajdata/caching/scene_cache.py
trajdata/data_structures/__init__.py
trajdata/data_structures/agent.py
trajdata/data_structures/batch.py
trajdata/data_structures/batch_element.py
trajdata/data_structures/collation.py
trajdata/data_structures/data_index.py
trajdata/data_structures/environment.py
trajdata/data_structures/scene.py
trajdata/data_structures/scene_metadata.py
trajdata/data_structures/scene_tag.py
trajdata/data_structures/state.py
trajdata/dataset_specific/__init__.py
trajdata/dataset_specific/raw_dataset.py
trajdata/dataset_specific/scene_records.py
trajdata/dataset_specific/argoverse2/__init__.py
trajdata/dataset_specific/argoverse2/av2_dataset.py
trajdata/dataset_specific/argoverse2/av2_utils.py
trajdata/dataset_specific/eth_ucy_peds/__init__.py
trajdata/dataset_specific/eth_ucy_peds/eupeds_dataset.py
trajdata/dataset_specific/interaction/__init__.py
trajdata/dataset_specific/interaction/interaction_dataset.py
trajdata/dataset_specific/lyft/__init__.py
trajdata/dataset_specific/lyft/lyft_dataset.py
trajdata/dataset_specific/lyft/lyft_utils.py
trajdata/dataset_specific/nuplan/__init__.py
trajdata/dataset_specific/nuplan/nuplan.yaml
trajdata/dataset_specific/nuplan/nuplan_dataset.py
trajdata/dataset_specific/nuplan/nuplan_utils.py
trajdata/dataset_specific/nusc/__init__.py
trajdata/dataset_specific/nusc/nusc_dataset.py
trajdata/dataset_specific/nusc/nusc_utils.py
trajdata/dataset_specific/sdd_peds/__init__.py
trajdata/dataset_specific/sdd_peds/estimated_homography.py
trajdata/dataset_specific/sdd_peds/sddpeds_dataset.py
trajdata/dataset_specific/vod/__init__.py
trajdata/dataset_specific/vod/vod_dataset.py
omega_prime_trajdata-1.4.1.5.dist-info/METADATA
omega_prime_trajdata-1.4.1.5.dist-info/WHEEL
omega_prime_trajdata-1.4.1.5.dist-info/entry_points.txt
omega_prime_trajdata-1.4.1.5.dist-info/licenses/LICENSE
omega_prime_trajdata-1.4.1.5.dist-info/RECORD
