Metadata-Version: 2.4
Name: omega-prime-trajdata
Version: 1.4.1.5
Summary: A fork of trajdata using betterproto2 and including a converter to omega-prime
Project-URL: Homepage, https://github.com/nvr-avg/trajdata
Project-URL: Bug Tracker, https://github.com/nvr-avg/trajdata/issues
Author-email: Michael Schuldes <michael.schuldes@rwth-aachen.de>
License-File: LICENSE
Classifier: Development Status :: 3 - Alpha
Classifier: Intended Audience :: Developers
Classifier: License :: OSI Approved :: Apache Software License
Classifier: Programming Language :: Python :: 3.12
Requires-Python: >=3.10
Requires-Dist: betterproto2-compiler
Requires-Dist: betterproto2<1,>=0.8
Requires-Dist: bokeh>=3.0.3
Requires-Dist: dill>=0.3.4
Requires-Dist: geopandas>=0.13.2
Requires-Dist: kornia>=0.6.4
Requires-Dist: matplotlib>=3.5
Requires-Dist: numpy>=2.0
Requires-Dist: omega-prime>=0.1.19
Requires-Dist: opencv-python>=4.5.0
Requires-Dist: pandas>=1.4.1
Requires-Dist: pyarrow>=7.0.0
Requires-Dist: scipy>=1.9.0
Requires-Dist: seaborn>=0.12
Requires-Dist: shapely>=2.0.0
Requires-Dist: torch>=1.10.2
Requires-Dist: tqdm>=4.62
Requires-Dist: zarr>=2.11.0
Provides-Extra: av2
Requires-Dist: av2==0.2.1; extra == 'av2'
Provides-Extra: dev
Requires-Dist: black; extra == 'dev'
Requires-Dist: build; extra == 'dev'
Requires-Dist: isort; extra == 'dev'
Requires-Dist: pytest; extra == 'dev'
Requires-Dist: pytest-xdist; extra == 'dev'
Requires-Dist: twine; extra == 'dev'
Provides-Extra: vod
Requires-Dist: vod-devkit==1.1.2; extra == 'vod'
Provides-Extra: waymo
Requires-Dist: intervaltree; extra == 'waymo'
Requires-Dist: tensorflow>=2.19.0; extra == 'waymo'
